huaweicloudsdkcodeartsdeploy/__init__.py
huaweicloudsdkcodeartsdeploy/v2/__init__.py
huaweicloudsdkcodeartsdeploy/v2/codeartsdeploy_async_client.py
huaweicloudsdkcodeartsdeploy/v2/codeartsdeploy_client.py
huaweicloudsdkcodeartsdeploy/v2/model/__init__.py
huaweicloudsdkcodeartsdeploy/v2/model/app_base_info.py
huaweicloudsdkcodeartsdeploy/v2/model/app_base_response.py
huaweicloudsdkcodeartsdeploy/v2/model/app_batch_delete_request.py
huaweicloudsdkcodeartsdeploy/v2/model/app_component_dao.py
huaweicloudsdkcodeartsdeploy/v2/model/app_delete_result.py
huaweicloudsdkcodeartsdeploy/v2/model/app_detail_info.py
huaweicloudsdkcodeartsdeploy/v2/model/app_execution_info.py
huaweicloudsdkcodeartsdeploy/v2/model/app_groups_entity.py
huaweicloudsdkcodeartsdeploy/v2/model/app_permission.py
huaweicloudsdkcodeartsdeploy/v2/model/application_permission_vo.py
huaweicloudsdkcodeartsdeploy/v2/model/batch_delete_app_request.py
huaweicloudsdkcodeartsdeploy/v2/model/batch_delete_app_response.py
huaweicloudsdkcodeartsdeploy/v2/model/batch_delete_hosts_request.py
huaweicloudsdkcodeartsdeploy/v2/model/batch_delete_hosts_response.py
huaweicloudsdkcodeartsdeploy/v2/model/batch_update_application_permissions_request.py
huaweicloudsdkcodeartsdeploy/v2/model/batch_update_application_permissions_request_body.py
huaweicloudsdkcodeartsdeploy/v2/model/batch_update_application_permissions_response.py
huaweicloudsdkcodeartsdeploy/v2/model/batch_update_permission_level_request.py
huaweicloudsdkcodeartsdeploy/v2/model/batch_update_permission_level_request_body.py
huaweicloudsdkcodeartsdeploy/v2/model/batch_update_permission_level_response.py
huaweicloudsdkcodeartsdeploy/v2/model/check_can_create_request.py
huaweicloudsdkcodeartsdeploy/v2/model/check_can_create_response.py
huaweicloudsdkcodeartsdeploy/v2/model/check_can_create_response_body_result.py
huaweicloudsdkcodeartsdeploy/v2/model/check_is_duplicate_app_name_request.py
huaweicloudsdkcodeartsdeploy/v2/model/check_is_duplicate_app_name_response.py
huaweicloudsdkcodeartsdeploy-3.1.184.dist-info/METADATA
huaweicloudsdkcodeartsdeploy-3.1.184.dist-info/WHEEL
huaweicloudsdkcodeartsdeploy-3.1.184.dist-info/licenses/LICENSE
huaweicloudsdkcodeartsdeploy-3.1.184.dist-info/RECORD
